txtstr/__init__.py
txtstr-2.1.0.dist-info/LICENSE
txtstr-2.1.0.dist-info/METADATA
txtstr-2.1.0.dist-info/WHEEL
txtstr-2.1.0.dist-info/top_level.txt
txtstr-2.1.0.dist-info/RECORD
