Metadata-Version: 2.1
Name: txtstr
Version: 2.1.0
Summary: Edit text file, encrypt and decrypt with python easily!
Home-page: https://github.com/PinguiMaya/txtstr
Author: PingüiMaya
Project-URL: Bug Tracker, https://github.com/PinguiMaya/txtstr/issues
Project-URL: Author Website, https://pingui.tk
Project-URL: Donate, https://www.paypal.com/donate/?hosted_button_id=V6V32NHTVP4GG
Classifier: Programming Language :: Python :: 3
Classifier: Operating System :: OS Independent
Requires-Python: >3.8
License-File: LICENSE
Requires-Dist: cryptography
Requires-Dist: docx
Requires-Dist: fpdf
